[
  {
    "createdAt": "2026-03-24T14:06:36Z",
    "doi": "doi:10.5072/FK2/LBSTAY",
    "name": "CNN Iran Conflict Metadata 2026-03-04",
    "croissant": "3371B",
    "py_croissant_1": "11660B"
  },
  {
    "createdAt": "2026-03-24T13:40:02Z",
    "doi": "doi:10.5072/FK2/22JJOI",
    "name": "Gravitational Mass Movement (\u00e2\u20ac\u02dcLandslide\u00e2\u20ac\u2122)",
    "croissant": "5043B",
    "py_croissant_1": "24183B"
  },
  {
    "createdAt": "2026-03-24T13:29:15Z",
    "doi": "doi:10.5072/FK2/XHP7WN",
    "name": "Acid Rain",
    "croissant": "4702B",
    "py_croissant_1": "21426B"
  },
  {
    "createdAt": "2026-01-28T16:26:22Z",
    "doi": "doi:10.5072/FK2/9DGDFN",
    "name": "Snowmelt Flooding",
    "croissant": "6103B",
    "py_croissant_1": "9725B"
  },
  {
    "createdAt": "2026-01-28T15:29:53Z",
    "doi": "doi:10.5072/FK2/FN88ZU",
    "name": "Blizzard",
    "croissant": "5455B",
    "py_croissant_1": "9720B"
  },
  {
    "createdAt": "2026-01-28T14:29:56Z",
    "doi": "doi:10.5072/FK2/GDTLFP",
    "name": "Snow",
    "croissant": "4907B",
    "py_croissant_1": "9735B"
  },
  {
    "createdAt": "2025-12-11T23:08:59Z",
    "doi": "doi:10.5072/FK2/GHXTXR",
    "name": "Random dataset to explore",
    "croissant": "2204B",
    "py_croissant_1": "55B"
  },
  {
    "createdAt": "2025-12-04T09:39:07Z",
    "doi": "doi:10.5072/FK2/KRKCNG",
    "name": "EDDI 2025 Hackathon example 1",
    "croissant": "2913B",
    "py_croissant_1": "12750B"
  },
  {
    "createdAt": "2025-11-27T09:18:16Z",
    "doi": "doi:10.5072/FK2/SAFMQU",
    "name": "Employement Data for each province",
    "croissant": "2174B",
    "py_croissant_1": "0B"
  },
  {
    "createdAt": "2025-11-27T09:18:47Z",
    "doi": "doi:10.5072/FK2/ON7W1G",
    "name": "Lunar Eclipse Data",
    "croissant": "3405B",
    "py_croissant_1": "21375B"
  },
  {
    "createdAt": "2025-11-27T10:22:21Z",
    "doi": "doi:10.5072/FK2/XAJSJ1",
    "name": "Smart Card Data",
    "croissant": "2147B",
    "py_croissant_1": "55B"
  },
  {
    "createdAt": "2025-11-27T09:20:50Z",
    "doi": "doi:10.5072/FK2/BNPFWG",
    "name": "Generated Time Series",
    "croissant": "3438B",
    "py_croissant_1": "55B"
  },
  {
    "createdAt": "2025-11-27T08:08:17Z",
    "doi": "doi:10.5072/FK2/BXSHPO",
    "name": "Earthquake dataset",
    "croissant": "5384B",
    "py_croissant_1": "0B"
  },
  {
    "createdAt": "2025-11-27T05:45:14Z",
    "doi": "doi:10.5072/FK2/6QKC3J",
    "name": "Worldbank test",
    "croissant": "14121B",
    "py_croissant_1": "184150B"
  },
  {
    "createdAt": "2025-11-26T20:04:08Z",
    "doi": "doi:10.5072/FK2/GAFUDD",
    "name": "Another random dataset",
    "croissant": "6890B",
    "py_croissant_1": "0B"
  },
  {
    "createdAt": "2025-11-19T10:37:11Z",
    "doi": "doi:10.5072/FK2/4ZSKVU",
    "name": "X-ray absorption spectra for K edge, selenium in sodium selenate",
    "croissant": "HTTP 502",
    "py_croissant_1": "HTTP 502"
  },
  {
    "createdAt": "2025-11-18T10:55:48Z",
    "doi": "doi:10.5072/FK2/8MODGT",
    "name": "Iron (II-III) oxide",
    "croissant": "HTTP 502",
    "py_croissant_1": "HTTP 502"
  },
  {
    "createdAt": "2025-11-19T07:30:23Z",
    "doi": "doi:10.5072/FK2/ZTZH3N",
    "name": "XAS - CDI - version 1.0: se_na2so4_rt.xdi",
    "croissant": "HTTP 502",
    "py_croissant_1": "HTTP 502"
  },
  {
    "createdAt": "2025-11-18T16:43:30Z",
    "doi": "doi:10.5072/FK2/T6XJID",
    "name": "GDP per capita test",
    "croissant": "HTTP 502",
    "py_croissant_1": "HTTP 502"
  },
  {
    "createdAt": "2025-11-17T16:02:53Z",
    "doi": "doi:10.5072/FK2/2TQRHJ",
    "name": "XAS test",
    "croissant": "HTTP 502",
    "py_croissant_1": "HTTP 502"
  },
  {
    "createdAt": "2025-11-14T10:24:51Z",
    "doi": "doi:10.5072/FK2/SPJJDT",
    "name": "Malawi ISC Emergencies",
    "croissant": "HTTP 502",
    "py_croissant_1": "HTTP 502"
  },
  {
    "createdAt": "2025-11-13T08:26:46Z",
    "doi": "doi:10.5072/FK2/RIB64Q",
    "name": "aut_core test",
    "croissant": "HTTP 502",
    "py_croissant_1": "HTTP 502"
  },
  {
    "createdAt": "2025-11-12T15:52:04Z",
    "doi": "doi:10.5072/FK2/X1NGOC",
    "name": "Simple variables",
    "croissant": "HTTP 502",
    "py_croissant_1": "HTTP 502"
  },
  {
    "createdAt": "2025-11-12T09:31:12Z",
    "doi": "doi:10.5072/FK2/DASWFN",
    "name": "Another test",
    "croissant": "HTTP 502",
    "py_croissant_1": "HTTP 502"
  },
  {
    "createdAt": "2025-11-11T16:51:41Z",
    "doi": "doi:10.5072/FK2/6TYU3O",
    "name": "Test with real data",
    "croissant": "HTTP 502",
    "py_croissant_1": "HTTP 502"
  },
  {
    "createdAt": "2025-11-10T15:34:23Z",
    "doi": "doi:10.5072/FK2/KQI5SN",
    "name": "CDIF test",
    "croissant": "HTTP 502",
    "py_croissant_1": "HTTP 502"
  },
  {
    "createdAt": "2025-11-10T13:56:09Z",
    "doi": "doi:10.5072/FK2/C2G6XB",
    "name": "Test CDIF in Croissant with python 1",
    "croissant": "HTTP 502",
    "py_croissant_1": "HTTP 502"
  }
]